aiida_eos/__init__.py
aiida_eos/eos.py
aiida_eos/rescale.py
aiida_eos-0.0.1.dist-info/entry_points.txt
aiida_eos-0.0.1.dist-info/LICENSE
aiida_eos-0.0.1.dist-info/WHEEL
aiida_eos-0.0.1.dist-info/METADATA
aiida_eos-0.0.1.dist-info/RECORD
