Metadata-Version: 2.1
Name: aiida_eos
Version: 0.0.1
Summary: AiiDA plugin to calculate the equation of state of a material.
Author-email: Chris Sewell <chrisj_sewell@hotmail.com>
Requires-Python: >=3.8
Classifier: License :: OSI Approved :: MIT License
Requires-Dist: aiida-core~=2.0
Requires-Dist: aiida-quantumespresso
Requires-Dist: ase
Requires-Dist: pytest ; extra == "test"
Requires-Dist: pytest-cov ; extra == "test"
Requires-Dist: pgtest ; extra == "test"
Provides-Extra: test
